pybroom.py
pybroom-0.2.dist-info/DESCRIPTION.rst
pybroom-0.2.dist-info/METADATA
pybroom-0.2.dist-info/RECORD
pybroom-0.2.dist-info/WHEEL
pybroom-0.2.dist-info/metadata.json
pybroom-0.2.dist-info/top_level.txt
