Metadata-Version: 2.0
Name: pybroom
Version: 0.2
Summary: Make tidy DataFrames from messy fit/model results.
Home-page: http://pybroom.readthedocs.io/
Author: Antonino Ingargiola
Author-email: tritemio@gmail.com
License: MIT
Download-URL: https://github.com/tritemio/pybroom
Keywords: dataframe tidy-data long-form model fitting tidyverse
Platform: Windows
Platform: Linux
Platform: Mac OS X
Classifier: Intended Audience :: Science/Research
Classifier: Operating System :: OS Independent
Classifier: Programming Language :: Python
Classifier: Programming Language :: Python :: 3.4
Classifier: Programming Language :: Python :: 3.5
Classifier: Topic :: Scientific/Engineering
Classifier: License :: OSI Approved :: MIT License
Requires-Dist: lmfit
Requires-Dist: pandas
